colour_text/__init__.py
colour_text/__main__.py
colour_text-1.0.5.dist-info/LICENSE
colour_text-1.0.5.dist-info/METADATA
colour_text-1.0.5.dist-info/WHEEL
colour_text-1.0.5.dist-info/entry_points.txt
colour_text-1.0.5.dist-info/top_level.txt
colour_text-1.0.5.dist-info/RECORD
