Metadata-Version: 2.1
Name: colour-text
Version: 1.0.5
Summary: colour_text that makes printing coloured text easier to do on Unix, macOS and Windows
Author-email: Barry Scott <barry@barrys-emacs.org>
License: Apache-2.0
Project-URL: Homepage, https://github.com/barry-scott/CLI-tools
Project-URL: Bug Tracker, https://github.com/barry-scott/CLI-tools/issues
Keywords: development
Classifier: Intended Audience :: End Users/Desktop
Classifier: Topic :: Utilities
Classifier: Environment :: Console
Classifier: Programming Language :: Python :: 3
Requires-Python: >=3.10
License-File: LICENSE
